{
  "start_pose": [
    -16.0,
    12.0
  ],
  "goal_pose_list": [
    [
      -15.6,
      20.8
    ],
    [
      -7.4,
      15.8
    ],
    [
      -5.0,
      13.0
    ],
    [
      -5.0,
      16.8
    ],
    [
      -15.0,
      -2.2
    ],
    [
      -4.8,
      -0.2
    ],
    [
      -14.8,
      -5.8
    ],
    [
      -3.0,
      -3.4
    ],
    [
      3.8,
      21.2
    ],
    [
      6.2,
      13.8
    ],
    [
      6.0,
      16.2
    ],
    [
      -0.6,
      -4.6
    ],
    [
      3.0,
      -2.0
    ],
    [
      6.6,
      19.4
    ],
    [
      2.2,
      -5.2
    ],
    [
      9.2,
      16.0
    ],
    [
      9.8,
      13.4
    ],
    [
      9.0,
      19.6
    ],
    [
      -13.6,
      -15.6
    ],
    [
      11.8,
      18.4
    ],
    [
      2.6,
      -12.6
    ],
    [
      13.4,
      -0.6
    ],
    [
      12.2,
      -3.8
    ],
    [
      2.6,
      -16.4
    ],
    [
      16.6,
      0.2
    ],
    [
      9.8,
      -14.0
    ],
    [
      5.4,
      -19.0
    ],
    [
      9.6,
      -19.8
    ]
  ],
  "start_corner_pixels": {
    "top_left": [
      60,
      40
    ],
    "height": 10,
    "width": 10
  },
  "goal_corner_pixels": [
    {
      "top_left": [
        19,
        45
      ],
      "height": 4,
      "width": 4
    },
    {
      "top_left": [
        44,
        86
      ],
      "height": 4,
      "width": 4
    },
    {
      "top_left": [
        58,
        98
      ],
      "height": 4,
      "width": 4
    },
    {
      "top_left": [
        39,
        98
      ],
      "height": 4,
      "width": 4
    },
    {
      "top_left": [
        134,
        48
      ],
      "height": 4,
      "width": 4
    },
    {
      "top_left": [
        124,
        99
      ],
      "height": 4,
      "width": 4
    },
    {
      "top_left": [
        152,
        49
      ],
      "height": 4,
      "width": 4
    },
    {
      "top_left": [
        140,
        108
      ],
      "height": 4,
      "width": 4
    },
    {
      "top_left": [
        17,
        142
      ],
      "height": 4,
      "width": 4
    },
    {
      "top_left": [
        54,
        154
      ],
      "height": 4,
      "width": 4
    },
    {
      "top_left": [
        42,
        153
      ],
      "height": 4,
      "width": 4
    },
    {
      "top_left": [
        146,
        120
      ],
      "height": 4,
      "width": 4
    },
    {
      "top_left": [
        133,
        138
      ],
      "height": 4,
      "width": 4
    },
    {
      "top_left": [
        26,
        156
      ],
      "height": 4,
      "width": 4
    },
    {
      "top_left": [
        149,
        134
      ],
      "height": 4,
      "width": 4
    },
    {
      "top_left": [
        43,
        169
      ],
      "height": 4,
      "width": 4
    },
    {
      "top_left": [
        56,
        172
      ],
      "height": 4,
      "width": 4
    },
    {
      "top_left": [
        25,
        168
      ],
      "height": 4,
      "width": 4
    },
    {
      "top_left": [
        201,
        55
      ],
      "height": 4,
      "width": 4
    },
    {
      "top_left": [
        31,
        182
      ],
      "height": 4,
      "width": 4
    },
    {
      "top_left": [
        186,
        136
      ],
      "height": 4,
      "width": 4
    },
    {
      "top_left": [
        126,
        190
      ],
      "height": 4,
      "width": 4
    },
    {
      "top_left": [
        142,
        184
      ],
      "height": 4,
      "width": 4
    },
    {
      "top_left": [
        205,
        136
      ],
      "height": 4,
      "width": 4
    },
    {
      "top_left": [
        122,
        206
      ],
      "height": 4,
      "width": 4
    },
    {
      "top_left": [
        193,
        172
      ],
      "height": 4,
      "width": 4
    },
    {
      "top_left": [
        218,
        150
      ],
      "height": 4,
      "width": 4
    },
    {
      "top_left": [
        222,
        171
      ],
      "height": 4,
      "width": 4
    }
  ]
}
