{
  "start_pose": [
    2.5,
    2.5
  ],
  "goal_pose_list": [
    [
      11.25,
      -25.25
    ],
    [
      16.25,
      8.5
    ],
    [
      7.5,
      2.75
    ],
    [
      18.25,
      -2.5
    ],
    [
      1.0,
      7.0
    ],
    [
      -23.5,
      4.75
    ],
    [
      -0.25,
      4.0
    ],
    [
      -22.0,
      1.0
    ],
    [
      -5.25,
      2.25
    ],
    [
      19.25,
      -7.25
    ],
    [
      13.0,
      5.0
    ],
    [
      -26.75,
      -0.25
    ],
    [
      -15.25,
      23.0
    ],
    [
      -20.25,
      7.25
    ],
    [
      -7.75,
      -9.75
    ],
    [
      4.25,
      5.5
    ],
    [
      18.0,
      4.25
    ],
    [
      -15.75,
      26.25
    ],
    [
      -13.75,
      -18.75
    ],
    [
      3.75,
      -1.75
    ],
    [
      -6.0,
      -2.25
    ],
    [
      -26.5,
      4.5
    ],
    [
      -5.75,
      -18.5
    ],
    [
      -19.0,
      27.0
    ],
    [
      -18.5,
      23.0
    ],
    [
      -5.75,
      17.0
    ],
    [
      20.75,
      20.75
    ],
    [
      -9.0,
      -18.5
    ],
    [
      19.5,
      9.0
    ],
    [
      -7.25,
      -6.0
    ]
  ],
  "start_corner_pixels": {
    "top_left": [
      110,
      130
    ],
    "height": 10,
    "width": 10
  },
  "goal_corner_pixels": [
    {
      "top_left": [
        224,
        168
      ],
      "height": 4,
      "width": 4
    },
    {
      "top_left": [
        89,
        188
      ],
      "height": 4,
      "width": 4
    },
    {
      "top_left": [
        112,
        153
      ],
      "height": 4,
      "width": 4
    },
    {
      "top_left": [
        133,
        196
      ],
      "height": 4,
      "width": 4
    },
    {
      "top_left": [
        95,
        127
      ],
      "height": 4,
      "width": 4
    },
    {
      "top_left": [
        104,
        29
      ],
      "height": 4,
      "width": 4
    },
    {
      "top_left": [
        107,
        122
      ],
      "height": 4,
      "width": 4
    },
    {
      "top_left": [
        119,
        35
      ],
      "height": 4,
      "width": 4
    },
    {
      "top_left": [
        114,
        102
      ],
      "height": 4,
      "width": 4
    },
    {
      "top_left": [
        152,
        200
      ],
      "height": 4,
      "width": 4
    },
    {
      "top_left": [
        103,
        175
      ],
      "height": 4,
      "width": 4
    },
    {
      "top_left": [
        124,
        16
      ],
      "height": 4,
      "width": 4
    },
    {
      "top_left": [
        31,
        62
      ],
      "height": 4,
      "width": 4
    },
    {
      "top_left": [
        94,
        42
      ],
      "height": 4,
      "width": 4
    },
    {
      "top_left": [
        162,
        92
      ],
      "height": 4,
      "width": 4
    },
    {
      "top_left": [
        101,
        140
      ],
      "height": 4,
      "width": 4
    },
    {
      "top_left": [
        106,
        195
      ],
      "height": 4,
      "width": 4
    },
    {
      "top_left": [
        18,
        60
      ],
      "height": 4,
      "width": 4
    },
    {
      "top_left": [
        198,
        68
      ],
      "height": 4,
      "width": 4
    },
    {
      "top_left": [
        130,
        138
      ],
      "height": 4,
      "width": 4
    },
    {
      "top_left": [
        132,
        99
      ],
      "height": 4,
      "width": 4
    },
    {
      "top_left": [
        105,
        17
      ],
      "height": 4,
      "width": 4
    },
    {
      "top_left": [
        197,
        100
      ],
      "height": 4,
      "width": 4
    },
    {
      "top_left": [
        15,
        47
      ],
      "height": 4,
      "width": 4
    },
    {
      "top_left": [
        31,
        49
      ],
      "height": 4,
      "width": 4
    },
    {
      "top_left": [
        55,
        100
      ],
      "height": 4,
      "width": 4
    },
    {
      "top_left": [
        40,
        206
      ],
      "height": 4,
      "width": 4
    },
    {
      "top_left": [
        197,
        87
      ],
      "height": 4,
      "width": 4
    },
    {
      "top_left": [
        87,
        201
      ],
      "height": 4,
      "width": 4
    },
    {
      "top_left": [
        147,
        94
      ],
      "height": 4,
      "width": 4
    }
  ]
}
