{
  "start_pose": [
    16.0,
    -14.0
  ],
  "goal_pose_list": [
    [
      5.4,
      -1.6
    ],
    [
      9.0,
      8.6
    ],
    [
      6.0,
      11.4
    ],
    [
      3.0,
      11.4
    ],
    [
      -19.8,
      6.8
    ]
  ],
  "start_corner_pixels": {
    "top_left": [
      190,
      200
    ],
    "height": 10,
    "width": 10
  },
  "goal_corner_pixels": [
    {
      "top_left": [
        131,
        150
      ],
      "height": 4,
      "width": 4
    },
    {
      "top_left": [
        80,
        168
      ],
      "height": 4,
      "width": 4
    },
    {
      "top_left": [
        66,
        153
      ],
      "height": 4,
      "width": 4
    },
    {
      "top_left": [
        66,
        138
      ],
      "height": 4,
      "width": 4
    },
    {
      "top_left": [
        89,
        24
      ],
      "height": 4,
      "width": 4
    }
  ]
}
