{
  "start_pose": [
    -15.0,
    -8.6
  ],
  "goal_pose_list": [
    [
      -13.2,
      -12.8
    ],
    [
      -15.0,
      -2.8
    ],
    [
      -9.2,
      -6.8
    ],
    [
      -12.0,
      -2.2
    ],
    [
      -7.8,
      -0.2
    ],
    [
      -10.6,
      4.0
    ],
    [
      -3.6,
      -18.0
    ],
    [
      -0.6,
      -15.0
    ],
    [
      0.6,
      -12.6
    ],
    [
      -8.8,
      6.4
    ],
    [
      -9.6,
      9.2
    ],
    [
      2.8,
      -17.0
    ],
    [
      8.8,
      -6.0
    ],
    [
      7.6,
      2.6
    ],
    [
      9.0,
      0.2
    ],
    [
      1.0,
      11.8
    ],
    [
      -6.8,
      17.4
    ],
    [
      11.6,
      -17.4
    ],
    [
      12.8,
      2.0
    ],
    [
      14.8,
      -9.2
    ],
    [
      14.8,
      -0.8
    ],
    [
      15.6,
      -15.4
    ],
    [
      15.2,
      4.6
    ],
    [
      18.4,
      1.2
    ],
    [
      11.2,
      15.6
    ]
  ],
  "start_corner_pixels": {
    "top_left": [
      163,
      45
    ],
    "height": 10,
    "width": 10
  },
  "goal_corner_pixels": [
    {
      "top_left": [
        187,
        57
      ],
      "height": 4,
      "width": 4
    },
    {
      "top_left": [
        137,
        48
      ],
      "height": 4,
      "width": 4
    },
    {
      "top_left": [
        157,
        77
      ],
      "height": 4,
      "width": 4
    },
    {
      "top_left": [
        134,
        63
      ],
      "height": 4,
      "width": 4
    },
    {
      "top_left": [
        124,
        84
      ],
      "height": 4,
      "width": 4
    },
    {
      "top_left": [
        103,
        70
      ],
      "height": 4,
      "width": 4
    },
    {
      "top_left": [
        213,
        105
      ],
      "height": 4,
      "width": 4
    },
    {
      "top_left": [
        198,
        120
      ],
      "height": 4,
      "width": 4
    },
    {
      "top_left": [
        186,
        126
      ],
      "height": 4,
      "width": 4
    },
    {
      "top_left": [
        91,
        79
      ],
      "height": 4,
      "width": 4
    },
    {
      "top_left": [
        77,
        75
      ],
      "height": 4,
      "width": 4
    },
    {
      "top_left": [
        208,
        137
      ],
      "height": 4,
      "width": 4
    },
    {
      "top_left": [
        153,
        167
      ],
      "height": 4,
      "width": 4
    },
    {
      "top_left": [
        110,
        161
      ],
      "height": 4,
      "width": 4
    },
    {
      "top_left": [
        122,
        168
      ],
      "height": 4,
      "width": 4
    },
    {
      "top_left": [
        64,
        128
      ],
      "height": 4,
      "width": 4
    },
    {
      "top_left": [
        36,
        89
      ],
      "height": 4,
      "width": 4
    },
    {
      "top_left": [
        210,
        181
      ],
      "height": 4,
      "width": 4
    },
    {
      "top_left": [
        113,
        187
      ],
      "height": 4,
      "width": 4
    },
    {
      "top_left": [
        169,
        197
      ],
      "height": 4,
      "width": 4
    },
    {
      "top_left": [
        127,
        197
      ],
      "height": 4,
      "width": 4
    },
    {
      "top_left": [
        200,
        201
      ],
      "height": 4,
      "width": 4
    },
    {
      "top_left": [
        100,
        199
      ],
      "height": 4,
      "width": 4
    },
    {
      "top_left": [
        117,
        215
      ],
      "height": 4,
      "width": 4
    },
    {
      "top_left": [
        45,
        179
      ],
      "height": 4,
      "width": 4
    }
  ]
}
