{
  "start_pose": [
    16.4,
    -9.2
  ],
  "goal_pose_list": [
    [
      -6.8,
      -10.6
    ],
    [
      -8.2,
      6.0
    ],
    [
      -15.6,
      -2.8
    ],
    [
      -11.6,
      9.0
    ],
    [
      -17.6,
      -0.4
    ]
  ],
  "start_corner_pixels": {
    "top_left": [
      166,
      202
    ],
    "height": 10,
    "width": 10
  },
  "goal_corner_pixels": [
    {
      "top_left": [
        176,
        89
      ],
      "height": 4,
      "width": 4
    },
    {
      "top_left": [
        93,
        82
      ],
      "height": 4,
      "width": 4
    },
    {
      "top_left": [
        137,
        45
      ],
      "height": 4,
      "width": 4
    },
    {
      "top_left": [
        78,
        65
      ],
      "height": 4,
      "width": 4
    },
    {
      "top_left": [
        125,
        35
      ],
      "height": 4,
      "width": 4
    }
  ]
}
