{
  "start_pose": [
    6.2,
    11.6
  ],
  "goal_pose_list": [
    [
      -0.6,
      16.4
    ],
    [
      17.4,
      9.4
    ],
    [
      -5.0,
      3.0
    ],
    [
      -8.8,
      2.4
    ],
    [
      -15.8,
      1.0
    ]
  ],
  "start_corner_pixels": {
    "top_left": [
      62,
      151
    ],
    "height": 10,
    "width": 10
  },
  "goal_corner_pixels": [
    {
      "top_left": [
        41,
        120
      ],
      "height": 4,
      "width": 4
    },
    {
      "top_left": [
        76,
        210
      ],
      "height": 4,
      "width": 4
    },
    {
      "top_left": [
        108,
        98
      ],
      "height": 4,
      "width": 4
    },
    {
      "top_left": [
        111,
        79
      ],
      "height": 4,
      "width": 4
    },
    {
      "top_left": [
        118,
        44
      ],
      "height": 4,
      "width": 4
    }
  ]
}
