{
  "start_pose": [
    -14.25,
    -1.5
  ],
  "goal_pose_list": [
    [
      -16.5,
      -15.0
    ],
    [
      1.25,
      19.25
    ],
    [
      -13.75,
      -9.0
    ],
    [
      -19.75,
      11.5
    ],
    [
      2.25,
      -11.75
    ],
    [
      -13.25,
      15.75
    ],
    [
      5.0,
      -19.25
    ],
    [
      -2.75,
      -7.25
    ],
    [
      20.0,
      13.75
    ],
    [
      17.5,
      -16.0
    ],
    [
      13.0,
      14.5
    ],
    [
      16.5,
      5.0
    ],
    [
      10.25,
      -1.5
    ],
    [
      9.25,
      8.75
    ],
    [
      5.25,
      0.0
    ],
    [
      -7.5,
      -3.5
    ],
    [
      -5.5,
      4.25
    ],
    [
      7.5,
      -9.25
    ],
    [
      -20.75,
      -6.0
    ],
    [
      5.75,
      12.5
    ],
    [
      11.25,
      -9.25
    ],
    [
      10.75,
      3.25
    ],
    [
      4.25,
      -7.5
    ],
    [
      12.75,
      10.25
    ],
    [
      9.0,
      -6.0
    ],
    [
      18.0,
      -2.5
    ],
    [
      9.5,
      -22.0
    ],
    [
      -17.75,
      -18.25
    ],
    [
      -23.0,
      -17.75
    ],
    [
      18.5,
      1.75
    ]
  ],
  "start_corner_pixels": {
    "top_left": [
      126,
      63
    ],
    "height": 10,
    "width": 10
  },
  "goal_corner_pixels": [
    {
      "top_left": [
        183,
        57
      ],
      "height": 4,
      "width": 4
    },
    {
      "top_left": [
        46,
        128
      ],
      "height": 4,
      "width": 4
    },
    {
      "top_left": [
        159,
        68
      ],
      "height": 4,
      "width": 4
    },
    {
      "top_left": [
        77,
        44
      ],
      "height": 4,
      "width": 4
    },
    {
      "top_left": [
        170,
        132
      ],
      "height": 4,
      "width": 4
    },
    {
      "top_left": [
        60,
        70
      ],
      "height": 4,
      "width": 4
    },
    {
      "top_left": [
        200,
        143
      ],
      "height": 4,
      "width": 4
    },
    {
      "top_left": [
        152,
        112
      ],
      "height": 4,
      "width": 4
    },
    {
      "top_left": [
        68,
        203
      ],
      "height": 4,
      "width": 4
    },
    {
      "top_left": [
        187,
        193
      ],
      "height": 4,
      "width": 4
    },
    {
      "top_left": [
        65,
        175
      ],
      "height": 4,
      "width": 4
    },
    {
      "top_left": [
        103,
        189
      ],
      "height": 4,
      "width": 4
    },
    {
      "top_left": [
        129,
        164
      ],
      "height": 4,
      "width": 4
    },
    {
      "top_left": [
        88,
        160
      ],
      "height": 4,
      "width": 4
    },
    {
      "top_left": [
        123,
        144
      ],
      "height": 4,
      "width": 4
    },
    {
      "top_left": [
        137,
        93
      ],
      "height": 4,
      "width": 4
    },
    {
      "top_left": [
        106,
        101
      ],
      "height": 4,
      "width": 4
    },
    {
      "top_left": [
        160,
        153
      ],
      "height": 4,
      "width": 4
    },
    {
      "top_left": [
        147,
        40
      ],
      "height": 4,
      "width": 4
    },
    {
      "top_left": [
        73,
        146
      ],
      "height": 4,
      "width": 4
    },
    {
      "top_left": [
        160,
        168
      ],
      "height": 4,
      "width": 4
    },
    {
      "top_left": [
        110,
        166
      ],
      "height": 4,
      "width": 4
    },
    {
      "top_left": [
        153,
        140
      ],
      "height": 4,
      "width": 4
    },
    {
      "top_left": [
        82,
        174
      ],
      "height": 4,
      "width": 4
    },
    {
      "top_left": [
        147,
        159
      ],
      "height": 4,
      "width": 4
    },
    {
      "top_left": [
        133,
        195
      ],
      "height": 4,
      "width": 4
    },
    {
      "top_left": [
        211,
        161
      ],
      "height": 4,
      "width": 4
    },
    {
      "top_left": [
        196,
        52
      ],
      "height": 4,
      "width": 4
    },
    {
      "top_left": [
        194,
        31
      ],
      "height": 4,
      "width": 4
    },
    {
      "top_left": [
        116,
        197
      ],
      "height": 4,
      "width": 4
    }
  ]
}
