{
  "start_pose": [
    -6.0,
    14.0
  ],
  "goal_pose_list": [
    [
      3.4,
      19.6
    ],
    [
      10.2,
      19.8
    ],
    [
      1.6,
      -3.0
    ],
    [
      -8.8,
      -5.4
    ],
    [
      4.8,
      -3.6
    ]
  ],
  "start_corner_pixels": {
    "top_left": [
      50,
      90
    ],
    "height": 10,
    "width": 10
  },
  "goal_corner_pixels": [
    {
      "top_left": [
        25,
        140
      ],
      "height": 4,
      "width": 4
    },
    {
      "top_left": [
        24,
        174
      ],
      "height": 4,
      "width": 4
    },
    {
      "top_left": [
        138,
        131
      ],
      "height": 4,
      "width": 4
    },
    {
      "top_left": [
        150,
        79
      ],
      "height": 4,
      "width": 4
    },
    {
      "top_left": [
        141,
        147
      ],
      "height": 4,
      "width": 4
    }
  ]
}
