{
  "start_pose": [
    -2.0,
    -22.0
  ],
  "goal_pose_list": [
    [
      3.6,
      -7.0
    ],
    [
      6.8,
      -7.4
    ],
    [
      5.0,
      -4.6
    ],
    [
      2.6,
      -3.8
    ],
    [
      -21.0,
      -21.8
    ],
    [
      -20.8,
      -18.6
    ],
    [
      7.4,
      -4.4
    ],
    [
      6.2,
      -2.0
    ],
    [
      2.4,
      -0.2
    ],
    [
      6.0,
      0.4
    ],
    [
      -12.2,
      3.2
    ],
    [
      -14.8,
      2.6
    ],
    [
      -17.4,
      2.2
    ],
    [
      -19.8,
      2.4
    ],
    [
      -13.6,
      6.4
    ],
    [
      -16.0,
      7.0
    ],
    [
      -18.6,
      5.6
    ],
    [
      -21.2,
      4.8
    ],
    [
      20.8,
      2.8
    ],
    [
      -13.4,
      11.0
    ],
    [
      -17.2,
      9.6
    ],
    [
      -21.8,
      8.0
    ],
    [
      -12.2,
      13.8
    ],
    [
      -19.6,
      11.2
    ],
    [
      -14.6,
      13.8
    ],
    [
      -17.2,
      13.8
    ],
    [
      -20.2,
      13.8
    ]
  ],
  "start_corner_pixels": {
    "top_left": [
      230,
      110
    ],
    "height": 10,
    "width": 10
  },
  "goal_corner_pixels": [
    {
      "top_left": [
        158,
        141
      ],
      "height": 4,
      "width": 4
    },
    {
      "top_left": [
        160,
        157
      ],
      "height": 4,
      "width": 4
    },
    {
      "top_left": [
        146,
        148
      ],
      "height": 4,
      "width": 4
    },
    {
      "top_left": [
        142,
        136
      ],
      "height": 4,
      "width": 4
    },
    {
      "top_left": [
        232,
        18
      ],
      "height": 4,
      "width": 4
    },
    {
      "top_left": [
        216,
        19
      ],
      "height": 4,
      "width": 4
    },
    {
      "top_left": [
        145,
        160
      ],
      "height": 4,
      "width": 4
    },
    {
      "top_left": [
        133,
        154
      ],
      "height": 4,
      "width": 4
    },
    {
      "top_left": [
        124,
        135
      ],
      "height": 4,
      "width": 4
    },
    {
      "top_left": [
        121,
        153
      ],
      "height": 4,
      "width": 4
    },
    {
      "top_left": [
        107,
        62
      ],
      "height": 4,
      "width": 4
    },
    {
      "top_left": [
        110,
        49
      ],
      "height": 4,
      "width": 4
    },
    {
      "top_left": [
        112,
        36
      ],
      "height": 4,
      "width": 4
    },
    {
      "top_left": [
        111,
        24
      ],
      "height": 4,
      "width": 4
    },
    {
      "top_left": [
        91,
        55
      ],
      "height": 4,
      "width": 4
    },
    {
      "top_left": [
        88,
        43
      ],
      "height": 4,
      "width": 4
    },
    {
      "top_left": [
        95,
        30
      ],
      "height": 4,
      "width": 4
    },
    {
      "top_left": [
        99,
        17
      ],
      "height": 4,
      "width": 4
    },
    {
      "top_left": [
        109,
        227
      ],
      "height": 4,
      "width": 4
    },
    {
      "top_left": [
        68,
        56
      ],
      "height": 4,
      "width": 4
    },
    {
      "top_left": [
        75,
        37
      ],
      "height": 4,
      "width": 4
    },
    {
      "top_left": [
        83,
        14
      ],
      "height": 4,
      "width": 4
    },
    {
      "top_left": [
        54,
        62
      ],
      "height": 4,
      "width": 4
    },
    {
      "top_left": [
        67,
        25
      ],
      "height": 4,
      "width": 4
    },
    {
      "top_left": [
        54,
        50
      ],
      "height": 4,
      "width": 4
    },
    {
      "top_left": [
        54,
        37
      ],
      "height": 4,
      "width": 4
    },
    {
      "top_left": [
        54,
        22
      ],
      "height": 4,
      "width": 4
    }
  ]
}
